Workbook

Sheet README
A1: GRC Exception & Risk-Remediation Ticket Tracker
A2: Fictional organization: Meridian Trust Financial (Canadian fintech) — for portfolio demonstration only
A4: Purpose
A5: This workbook tracks the full lifecycle of GRC exception tickets, policy deviations, and risk-acceptance
A6: requests from intake through closure. It supports ISO/IEC 27001:2022 (Clause 6.1.3, Annex A.5.36,
A7: A.8.9), NIST SP 800-53 Rev. 5 (CA-5 Plan of Action and Milestones, PM-4 Plan of Action Management),
A8: and NIST SP 800-161 (supply chain risk exceptions).
A10: How to use this workbook
A11: 1. Ticket Register — the master log. One row per ticket. Use the dropdown lists for standardized fields.
A12: 2. Dashboard — auto-calculated summary of open/overdue tickets, aging, and risk distribution.
A13: 3. Lookup Lists — controls the dropdown values used across the register (edit here to adjust options).
A14: 4. SLA Matrix — defines target turnaround time by residual risk rating; feeds the SLA Due Date formula.
... A24: documents the 7-stage lifecycle, RACI, SLA model, KPIs, and control mapping in narrative form.

Sheet Lookup Lists
A1: Exception Type | B1: Inherent/Residual Risk Rating | C1: Approval Status | D1: Ticket Status | E1: Control Domain (ISO 27001:2022 Annex A / NIST 800-53 Family) | F1: SLA Status (calculated, reference only)
A2: Policy Exception | B2: Critical | C2: Pending Approval | D2: Open | E2: A.5 Access Control / AC | F2: On Track
A3: Risk Acceptance | B3: High | C3: Approved | D3: Pending Approval | E3: A.8.9 Configuration Management / CM | F3: Due Soon
A4: Standard Deviation | B4: Medium | C4: Approved with Conditions | D4: In Remediation | E4: A.8.16 Monitoring / AU | F4: Overdue
A5: Compensating Control | B5: Low | C5: Rejected | D5: Pending Verification | E5: A.5.19 Supplier Relationships / SA & SR (800-161) | F5: Closed
A6: Temporary Waiver | C6: Escalated to Risk Committee | D6: Reopened | E6: A.8.24 Cryptography / SC
D7: Closed | E7: A.8.8 Vulnerability Management / RA
D8: Rejected | E8: A.5.29 ICT Continuity / CP
E9: A.5.36 Compliance Review / CA

Sheet SLA Matrix
A1: Residual Risk Rating | B1: SLA Target (Days to Closure) | C1: Review/Re-certification Frequency | D1: Escalation Trigger
A2: Critical | B2: 15 | C2: Every 90 days | D2: No remediation owner assigned within 2 business days
A3: High | B3: 30 | C3: Every 180 days | D3: 50% of SLA elapsed with no remediation plan on file
A4: Medium | B4: 60 | C4: Annually | D4: SLA breached by more than 10 days
A5: Low | B5: 90 | C5: Annually | D5: SLA breached by more than 20 days

Sheet Ticket Register
A1: Ticket ID | B1: Date Raised | C1: Requestor | D1: Business Unit | E1: System / Asset | F1: Control Domain | G1: Control Reference | H1: Exception Type | I1: Description | J1: Inherent Risk Rating | K1: Compensating Controls | L1: Residual Risk Rating | M1: Risk Owner | N1: Approver | O1: Approval Status | P1: Approval Date | Q1: SLA Target (Days) | R1: SLA Due Date | S1: Remediation Owner | T1: Remediation Plan Summary | U1: Target Closure Date | V1: Actual Closure Date | W1: Ticket Status | X1: Days Open | Y1: SLA Status | Z1: Next Review Date | AA1: Reopened Count | AB1: Closure Evidence Ref.
A2: RXT-2026-001 | B2: 46088 | C2: D. Alaba (IT Ops) | D2: Retail Banking Tech | E2: Core Banking Gateway API | F2: A.5.19 Supplier Relationships / SA & SR (800-161) | G2: SR-3, ISO A.5.19-A.5.22 | H2: Risk Acceptance | I2: Third-party payment processor delayed SOC 2 Type II report beyond contractual deadline. | J2: High | K2: Monthly vendor call, interim attestation letter, enhanced transaction monitoring | L2: Medium | M2: M. Okonkwo (TPRM Lead) | N2: Chief Risk Officer | O2: Approved with Conditions | P2: 46098 | Q2: =IFERROR(VLOOKUP(L2,'SLA Matrix'!$A$2:$B$5,2,FALSE()),"") -> 60 | R2: =IF(P2="","",IF(Q2="","",P2+Q2)) -> 46158 | S2: M. Okonkwo | T2: Obtain SOC 2 Type II report; re-assess residual rating on receipt. | U2: 46188 | V2: 46190 | W2: Closed | X2: =IF(V2<>"",V2-B2,TODAY()-B2) -> 102 | Y2: =IF(W2="Closed","Closed",IF(R2="","N/A",IF(TODAY()>R2,"Overdue",IF(R2-TODAY()<=5,"Due Soon","On Track")))) -> Closed | Z2: =IF(P2="","",P2+365) -> 46463 | AA2: 0 | AB2: EVID-2026-001-SOC2.pdf
A3: RXT-2026-002 | B3: 46113 | C3: S. Choudhury (Infra) | D3: Enterprise IT | E3: Legacy File Server (WIN-FS02) | F3: A.8.24 Cryptography / SC | G3: SC-13, ISO A.8.24 | H3: Standard Deviation | I3: Server cannot support TLS 1.2 due to end-of-life OS; scheduled for decommission. | J3: High | K3: Network segmentation, restricted ACLs, decommission project underway | L3: High | M3: S. Choudhury | N3: CISO | O3: Approved with Conditions | P3: 46120 | Q3: =IFERROR(VLOOKUP(L3,'SLA Matrix'!$A$2:$B$5,2,FALSE()),"") -> 30 | R3: =IF(P3="","",IF(Q3="","",P3+Q3)) -> 46150 | S3: S. Choudhury | T3: Migrate file shares to hardened NAS; decommission WIN-FS02. | U3: 46203 | W3: In Remediation | X3: =IF(V3<>"",V3-B3,TODAY()-B3) -> 96 | Y3: =IF(W3="Closed","Closed",IF(R3="","N/A",IF(TODAY()>R3,"Overdue",IF(R3-TODAY()<=5,"Due Soon","On Track")))) -> Overdue | Z3: =IF(P3="","",P3+365) -> 46485 | AA3: 0
A4: RXT-2026-003 | B4: 46128 | C4: A. Nwosu (App Dev) | D4: Digital Banking | E4: Mobile Banking App v4.2 | F4: A.8.8 Vulnerability Management / RA | G4: RA-5, ISO A.8.8 | H4: Policy Exception | I4: Medium-severity dependency vulnerability (outdated logging library) cannot be patched before next release window. | J4: Medium | K4: WAF rule added, dependency isolated from user input path | L4: Low | M4: A. Nwosu | N4: App Security Lead | O4: Approved | P4: 46133 | Q4: =IFERROR(VLOOKUP(L4,'SLA Matrix'!$A$2:$B$5,2,FALSE()),"") -> 90 | R4: =IF(P4="","",IF(Q4="","",P4+Q4)) -> 46223 | S4: A. Nwosu | T4: Upgrade library in Q3 release cycle; retest. | U4: 46193 | V4: 46194 | W4: Closed | X4: =IF(V4<>"",V4-B4,TODAY()-B4) -> 66 | Y4: =IF(W4="Closed","Closed",IF(R4="","N/A",IF(TODAY()>R4,"Overdue",IF(R4-TODAY()<=5,"Due Soon","On Track")))) -> Closed | Z4: =IF(P4="","",P4+365) -> 46498 | AA4: 0 | AB4: EVID-2026-003-scan.pdf
A5: RXT-2026-004 | B5: 46148 | C5: P. Osei (Access Mgmt) | D5: Human Resources | E5: HR Information System (Workday) | F5: A.5 Access Control / AC | G5: AC-6, ISO A.5.15-A.5.18 | H5: Policy Exception | I5: Contractor requires temporary elevated access beyond standard least-privilege baseline for payroll migration. | J5: Medium | K5: Time-boxed access (30 days), session logging enabled, manager sign-off | L5: Low | M5: P. Osei | N5: HR Director | O5: Approved | P5: 46150 | Q5: =IFERROR(VLOOKUP(L5,'SLA Matrix'!$A$2:$B$5,2,FALSE()),"") -> 90 | R5: =IF(P5="","",IF(Q5="","",P5+Q5)) -> 46240 | S5: P. Osei | T5: Revoke elevated access automatically at expiry; confirm via access review. | U5: 46180 | V5: 46180 | W5: Closed | X5: =IF(V5<>"",V5-B5,TODAY()-B5) -> 32 | Y5: =IF(W5="Closed","Closed",IF(R5="","N/A",IF(TODAY()>R5,"Overdue",IF(R5-TODAY()<=5,"Due Soon","On Track")))) -> Closed | Z5: =IF(P5="","",P5+365) -> 46515 | AA5: 0 | AB5: EVID-2026-004-access.pdf
A6: RXT-2026-005 | B6: 46153 | C6: T. Fagbenle (SOC) | D6: Security Operations | E6: SIEM Log Retention Policy | F6: A.8.16 Monitoring / AU | G6: AU-11, ISO A.8.16 | H6: Standard Deviation | I6: Cloud log retention configured for 180 days instead of policy-mandated 365 days due to storage cost cap. | J6: Medium | K6: Cold storage archive of logs beyond 180 days at reduced query capability | L6: Medium | M6: T. Fagbenle | N6: CISO | O6: Escalated to Risk Committee | Q6: =IFERROR(VLOOKUP(L6,'SLA Matrix'!$A$2:$B$5,2,FALSE()),"") -> 60 | R6: =IF(P6="","",IF(Q6="","",P6+Q6)) | S6: T. Fagbenle | T6: Present storage cost-benefit options to Risk Committee for final retention decision. | U6: 46218 | W6: Pending Approval | X6: =IF(V6<>"",V6-B6,TODAY()-B6) -> 56 | Y6: =IF(W6="Closed","Closed",IF(R6="","N/A",IF(TODAY()>R6,"Overdue",IF(R6-TODAY()<=5,"Due Soon","On Track")))) -> N/A | Z6: =IF(P6="","",P6+365) | AA6: 0
A7: RXT-2026-006 | B7: 46160 | C7: R. Adebayo (Vendor Mgmt) | D7: Procurement | E7: Cloud Backup Provider (NorthVault) | F7: A.5.19 Supplier Relationships / SA & SR (800-161) | G7: SR-6, ISO A.5.20 | H7: Risk Acceptance | I7: Vendor data processing agreement lacks explicit sub-processor notification clause required by internal standard. | J7: Medium | K7: Quarterly sub-processor list requested manually pending contract renewal | L7: Medium | M7: R. Adebayo | N7: Chief Risk Officer | O7: Approved with Conditions | P7: 46168 | Q7: =IFERROR(VLOOKUP(L7,'SLA Matrix'!$A$2:$B$5,2,FALSE()),"") -> 60 | R7: =IF(P7="","",IF(Q7="","",P7+Q7)) -> 46228 | S7: R. Adebayo | T7: Renegotiate DPA clause at next contract renewal (Q4 2026). | U7: 46298 | W7: In Remediation | X7: =IF(V7<>"",V7-B7,TODAY()-B7) -> 49 | Y7: =IF(W7="Closed","Closed",IF(R7="","N/A",IF(TODAY()>R7,"Overdue",IF(R7-TODAY()<=5,"Due Soon","On Track")))) -> On Track | Z7: =IF(P7="","",P7+365) -> 46533 | AA7: 0
A8: RXT-2026-007 | B8: 46168 | C8: C. Mensah (BCP) | D8: Business Continuity | E8: Disaster Recovery Site (Ottawa DC) | F8: A.5.29 ICT Continuity / CP | G8: CP-7, ISO A.5.29-A.5.30 | H8: Compensating Control | I8: Annual DR failover test postponed due to data centre maintenance window conflict. | J8: High | K8: Tabletop exercise conducted in lieu; full failover rescheduled | L8: Medium | M8: C. Mensah | N8: COO | O8: Approved with Conditions | P8: 46173 | Q8: =IFERROR(VLOOKUP(L8,'SLA Matrix'!$A$2:$B$5,2,FALSE()),"") -> 60 | R8: =IF(P8="","",IF(Q8="","",P8+Q8)) -> 46233 | S8: C. Mensah | T8: Execute full failover test within 60 days of original schedule. | U8: 46206 | W8: Reopened | X8: =IF(V8<>"",V8-B8,TODAY()-B8) -> 41 | Y8: =IF(W8="Closed","Closed",IF(R8="","N/A",IF(TODAY()>R8,"Overdue",IF(R8-TODAY()<=5,"Due Soon","On Track")))) -> On Track | Z8: =IF(P8="","",P8+365) -> 46538 | AA8: 1
A9: RXT-2026-008 | B9: 46178 | C9: K. Boateng (App Dev) | D9: Digital Banking | E9: Customer Portal Authentication | F9: A.5 Access Control / AC | G9: AC-7, IA-5, ISO A.8.5 | H9: Policy Exception | I9: MFA enrolment grace period extended for customers migrating from legacy authentication method. | J9: Medium | K9: Risk-based step-up authentication, fraud monitoring alerts enabled | L9: Low | M9: K. Boateng | N9: CISO | O9: Approved | P9: 46180 | Q9: =IFERROR(VLOOKUP(L9,'SLA Matrix'!$A$2:$B$5,2,FALSE()),"") -> 90 | R9: =IF(P9="","",IF(Q9="","",P9+Q9)) -> 46270 | S9: K. Boateng | T9: Complete MFA migration campaign; disable legacy path. | U9: 46228 | W9: In Remediation | X9: =IF(V9<>"",V9-B9,TODAY()-B9) -> 31 | Y9: =IF(W9="Closed","Closed",IF(R9="","N/A",IF(TODAY()>R9,"Overdue",IF(R9-TODAY()<=5,"Due Soon","On Track")))) -> On Track | Z9: =IF(P9="","",P9+365) -> 46545 | AA9: 0
A10: RXT-2026-009 | B10: 46183 | C10: N. Eze (IT Ops) | D10: Enterprise IT | E10: Patch Management Baseline | F10: A.8.8 Vulnerability Management / RA | G10: SI-2, ISO A.8.8 | H10: Standard Deviation | I10: Critical OS patch deployment delayed on 12 servers pending change freeze during quarter-end processing. | J10: High | K10: Additional network monitoring and IDS tuning on affected hosts | L10: High | M10: N. Eze | N10: CISO | O10: Pending Approval | Q10: =IFERROR(VLOOKUP(L10,'SLA Matrix'!$A$2:$B$5,2,FALSE()),"") -> 30 | R10: =IF(P10="","",IF(Q10="","",P10+Q10)) | S10: N. Eze | T10: Deploy patches immediately after change freeze lifts. | U10: 46215 | W10: Open | X10: =IF(V10<>"",V10-B10,TODAY()-B10) -> 26 | Y10: =IF(W10="Closed","Closed",IF(R10="","N/A",IF(TODAY()>R10,"Overdue",IF(R10-TODAY()<=5,"Due Soon","On Track")))) -> N/A | Z10: =IF(P10="","",P10+365) | AA10: 0
A11: RXT-2026-010 | B11: 46190 | C11: F. Ibrahim (Data Governance) | D11: Data & Analytics | E11: Customer Data Warehouse | F11: A.8.9 Configuration Management / CM | G11: CM-3, ISO A.8.9 | H11: Policy Exception | I11: Emergency schema change deployed outside standard change-approval window to fix production reporting outage. | J11: Medium | K11: Post-implementation review scheduled; rollback plan documented | L11: Low | M11: F. Ibrahim | N11: Change Advisory Board Chair | O11: Approved | P11: 46191 | Q11: =IFERROR(VLOOKUP(L11,'SLA Matrix'!$A$2:$B$5,2,FALSE()),"") -> 90 | R11: =IF(P11="","",IF(Q11="","",P11+Q11)) -> 46281 | S11: F. Ibrahim | T11: Complete retrospective change review and update CAB record. | U11: 46198 | V11: 46199 | W11: Closed | X11: =IF(V11<>"",V11-B11,TODAY()-B11) -> 9 | Y11: =IF(W11="Closed","Closed",IF(R11="","N/A",IF(TODAY()>R11,"Overdue",IF(R11-TODAY()<=5,"Due Soon","On Track")))) -> Closed | Z11: =IF(P11="","",P11+365) -> 46556 | AA11: 0 | AB11: EVID-2026-010-CAB.pdf
A12: RXT-2026-011 | B12: 46194 | C12: J. Adeyemi (SOC) | D12: Security Operations | E12: Endpoint Detection & Response (EDR) | F12: A.8.16 Monitoring / AU | G12: SI-4, ISO A.8.16 | H12: Temporary Waiver | I12: EDR agent rollout delayed on 40 field-sales laptops due to VPN bandwidth constraints. | J12: Medium | K12: Interim host-based firewall hardening and manual log review | L12: Medium | M12: J. Adeyemi | N12: CISO | O12: Approved with Conditions | P12: 46198 | Q12: =IFERROR(VLOOKUP(L12,'SLA Matrix'!$A$2:$B$5,2,FALSE()),"") -> 60 | R12: =IF(P12="","",IF(Q12="","",P12+Q12)) -> 46258 | S12: J. Adeyemi | T12: Stagger EDR rollout in batches over next 3 weeks via off-peak sync. | U12: 46223 | W12: In Remediation | X12: =IF(V12<>"",V12-B12,TODAY()-B12) -> 15 | Y12: =IF(W12="Closed","Closed",IF(R12="","N/A",IF(TODAY()>R12,"Overdue",IF(R12-TODAY()<=5,"Due Soon","On Track")))) -> On Track | Z12: =IF(P12="","",P12+365) -> 46563 | AA12: 0
A13: RXT-2026-012 | B13: 46198 | C13: L. Adesanya (Legal) | D13: Legal & Compliance | E13: Records Retention Schedule | F13: A.5.36 Compliance Review / CA | G13: CA-5, ISO A.5.36 | H13: Risk Acceptance | I13: Archived contract records retained 2 years beyond regulatory disposal date pending litigation hold review. | J13: Low | K13: Records isolated in restricted-access legal hold vault | L13: Low | M13: L. Adesanya | N13: General Counsel | O13: Approved | P13: 46200 | Q13: =IFERROR(VLOOKUP(L13,'SLA Matrix'!$A$2:$B$5,2,FALSE()),"") -> 90 | R13: =IF(P13="","",IF(Q13="","",P13+Q13)) -> 46290 | S13: L. Adesanya | T13: Release litigation hold and initiate disposal per schedule. | U13: 46253 | W13: Open | X13: =IF(V13<>"",V13-B13,TODAY()-B13) -> 11 | Y13: =IF(W13="Closed","Closed",IF(R13="","N/A",IF(TODAY()>R13,"Overdue",IF(R13-TODAY()<=5,"Due Soon","On Track")))) -> On Track | Z13: =IF(P13="","",P13+365) -> 46565 | AA13: 0
A14: RXT-2026-013 | B14: 46201 | C14: B. Yusuf (Infra) | D14: Enterprise IT | E14: Firewall Rule Set (Perimeter) | F14: A.5 Access Control / AC | G14: AC-4, ISO A.8.20 | H14: Standard Deviation | I14: Broad outbound rule left temporarily open to support vendor data migration cutover. | J14: High | K14: Rule scoped to single vendor IP range with expiry date set | L14: Medium | M14: B. Yusuf | N14: CISO | O14: Approved with Conditions | P14: 46202 | Q14: =IFERROR(VLOOKUP(L14,'SLA Matrix'!$A$2:$B$5,2,FALSE()),"") -> 60 | R14: =IF(P14="","",IF(Q14="","",P14+Q14)) -> 46262 | S14: B. Yusuf | T14: Remove firewall rule immediately after migration cutover confirmed complete. | U14: 46211 | W14: Open | X14: =IF(V14<>"",V14-B14,TODAY()-B14) -> 8 | Y14: =IF(W14="Closed","Closed",IF(R14="","N/A",IF(TODAY()>R14,"Overdue",IF(R14-TODAY()<=5,"Due Soon","On Track")))) -> On Track | Z14: =IF(P14="","",P14+365) -> 46567 | AA14: 0
A15: RXT-2026-014 | B15: 46204 | C15: H. Suleiman (App Dev) | D15: Digital Banking | E15: API Gateway Rate Limiting | F15: A.8.24 Cryptography / SC | G15: SC-5, ISO A.8.23 | H15: Policy Exception | I15: Rate-limiting thresholds temporarily relaxed to support partner onboarding load test. | J15: Medium | K15: Enhanced WAF monitoring and automatic rollback trigger configured | L15: Low | M15: H. Suleiman | N15: App Security Lead | O15: Pending Approval | Q15: =IFERROR(VLOOKUP(L15,'SLA Matrix'!$A$2:$B$5,2,FALSE()),"") -> 90 | R15: =IF(P15="","",IF(Q15="","",P15+Q15)) | S15: H. Suleiman | T15: Restore standard thresholds after load test window closes. | U15: 46210 | W15: Open | X15: =IF(V15<>"",V15-B15,TODAY()-B15) -> 5 | Y15: =IF(W15="Closed","Closed",IF(R15="","N/A",IF(TODAY()>R15,"Overdue",IF(R15-TODAY()<=5,"Due Soon","On Track")))) -> N/A | Z15: =IF(P15="","",P15+365) | AA15: 0
A16: RXT-2026-015 | B16: 46206 | C16: O. Balogun (TPRM) | D16: Procurement | E16: HR Payroll Outsourcing Vendor | F16: A.5.19 Supplier Relationships / SA & SR (800-161) | G16: SR-2, ISO A.5.21 | H16: Risk Acceptance | I16: Vendor annual penetration test report overdue by 3 weeks; renewal contract under negotiation. | J16: Medium | K16: Interim vulnerability self-attestation obtained from vendor | L16: Medium | M16: O. Balogun | N16: Chief Risk Officer | O16: Pending Approval | Q16: =IFERROR(VLOOKUP(L16,'SLA Matrix'!$A$2:$B$5,2,FALSE()),"") -> 60 | R16: =IF(P16="","",IF(Q16="","",P16+Q16)) | S16: O. Balogun | T16: Obtain overdue pen-test report and reassess before contract renewal signature. | U16: 46233 | W16: Open | X16: =IF(V16<>"",V16-B16,TODAY()-B16) -> 3 | Y16: =IF(W16="Closed","Closed",IF(R16="","N/A",IF(TODAY()>R16,"Overdue",IF(R16-TODAY()<=5,"Due Soon","On Track")))) -> N/A | Z16: =IF(P16="","",P16+365) | AA16: 0

Sheet Dashboard
A1: GRC Exception Ticket Dashboard
A2: Meridian Trust Financial — live summary (auto-calculated from Ticket Register)
A4: Tickets by Status | D4: Open Tickets by Residual Risk
A5: Open | B5: =COUNTIF('Ticket Register'!$W$2:$W$16,A5) -> 5 | D5: Critical | E5: =COUNTIFS('Ticket Register'!$L$2:$L$16,D5,'Ticket Register'!$W$2:$W$16,"<>Closed",'Ticket Register'!$W$2:$W$16,"<>Rejected") -> 0
A6: Pending Approval | B6: =COUNTIF('Ticket Register'!$W$2:$W$16,A6) -> 1 | D6: High | E6: =COUNTIFS('Ticket Register'!$L$2:$L$16,D6,'Ticket Register'!$W$2:$W$16,"<>Closed",'Ticket Register'!$W$2:$W$16,"<>Rejected") -> 2
A7: In Remediation | B7: =COUNTIF('Ticket Register'!$W$2:$W$16,A7) -> 4 | D7: Medium | E7: =COUNTIFS('Ticket Register'!$L$2:$L$16,D7,'Ticket Register'!$W$2:$W$16,"<>Closed",'Ticket Register'!$W$2:$W$16,"<>Rejected") -> 6
A8: Pending Verification | B8: =COUNTIF('Ticket Register'!$W$2:$W$16,A8) -> 0 | D8: Low | E8: =COUNTIFS('Ticket Register'!$L$2:$L$16,D8,'Ticket Register'!$W$2:$W$16,"<>Closed",'Ticket Register'!$W$2:$W$16,"<>Rejected") -> 3
A9: Reopened | B9: =COUNTIF('Ticket Register'!$W$2:$W$16,A9) -> 1
A10: Closed | B10: =COUNTIF('Ticket Register'!$W$2:$W$16,A10) -> 4
A11: Rejected | B11: =COUNTIF('Ticket Register'!$W$2:$W$16,A11) -> 0
A12: Total | B12: =SUM(B5:B11) -> 15
A14: SLA Health (open tickets only) | D14: Aging Metrics
A15: Overdue | B15: =COUNTIFS('Ticket Register'!$Y$2:$Y$16,"Overdue") -> 1 | D15: Average days open (all tickets) | E15: =ROUND(AVERAGE('Ticket Register'!$X$2:$X$16),1) -> 36.7
A16: Due Soon (<=5 days) | B16: =COUNTIFS('Ticket Register'!$Y$2:$Y$16,"Due Soon") -> 0 | D16: Longest open ticket (days) | E16: =MAX('Ticket Register'!$X$2:$X$16) -> 102
A17: On Track | B17: =COUNTIFS('Ticket Register'!$Y$2:$Y$16,"On Track") -> 6 | D17: Tickets reopened (total) | E17: =SUM('Ticket Register'!$AA$2:$AA$16) -> 1
